example/__init__.py
example/app_service.py
example/main.py
example/todo_example.py
example/user/__init__.py
example/user/user_service.py
example/user/dto/__init__.py
example/user/dto/user_create_dto.py
example/user/dto/user_response_dto.py
example/user/dto/user_update_dto.py
example/user/entity/__init__.py
example/user/entity/post_entity.py
example/user/entity/user_entity.py
ezyapi/__init__.py
ezyapi/config.py
ezyapi/core.py
ezyapi/database.py
ezyapi/api/__init__.py
ezyapi/api/core.py
ezyapi/database/__init__.py
ezyapi/database/config.py
ezyapi/database/decorators.py
ezyapi/database/entity.py
ezyapi/database/filters.py
ezyapi/database/relationships.py
ezyapi/database/repositories/__init__.py
ezyapi/database/repositories/base.py
ezyapi/database/repositories/mongodb.py
ezyapi/database/repositories/mysql.py
ezyapi/database/repositories/postgres.py
ezyapi/database/repositories/sqlite.py
ezyapi/decorators/__init__.py
ezyapi/decorators/route.py
ezyapi/dto/__init__.py
ezyapi/dto/base.py
ezyapi/entity/__init__.py
ezyapi/filters/__init__.py
ezyapi/repositories/__init__.py
ezyapi/repositories/base.py
ezyapi/repositories/mongodb.py
ezyapi/repositories/mysql.py
ezyapi/repositories/postgresql.py
ezyapi/repositories/sqlite.py
ezyapi/service/__init__.py
ezyapi/service/base.py
ezyapi/services/__init__.py
ezyapi/services/base.py
ezyapi/utils/__init__.py
ezyapi/utils/inflection.py
ezycli/__init__.py
ezycli/commands.py
ezyapi-1.7.7.dist-info/METADATA
ezyapi-1.7.7.dist-info/WHEEL
ezyapi-1.7.7.dist-info/entry_points.txt
ezyapi-1.7.7.dist-info/top_level.txt
ezyapi-1.7.7.dist-info/RECORD
